{
  "pp_params": {
    "cat_params": {
      "max_perc_miss_for_most_freq_impute": 0.1,
      "forced_missing_perc": 0.03,
      "rare_perc_threshold": 0.03
    },
    "num_params": {
      "missing_ind_suffix": "_missing",
      "forced_missing_perc": 0.03
    },
    "pp_step_names": {
      "COLUMN_SELECTOR": "column_selector",
      "STRING_TYPE_CASTER": "string_type_caster",
      "FLOAT_TYPE_CASTER": "float_type_caster",
      "DROP_NA_TRANSFORMER": "drop_na_transformer",
      "DROP_FEATURES": "drop_features",
      "CAT_IMPUTER_MISSING": "cat_imputation_missing",
      "CAT_IMPUTER_FREQ": "cat_imputation_freq",

      "NUM_MISSING_INDICATOR": "num_missing_indicator",
      "NUM_MISSING_MEAN_IMPUTER": "num_missing_mean_imputer",
      "CAT_RARE_LABEL_ENCODER": "rare_label_encoder",
      "MINMAX_BOUNDER": "minmax_bounder",
      "YEO_JOHN_TRANSFORMER": "yeo_john_transformer",
      "QUINTILE_TRANSFORMER": "quintile_transformer",
      "MIN_MAX_SCALER": "min_max_scaler",
      "STANDARD_SCALER": "standard_scaler",
      "ONE_HOT_ENCODER": "one_hot_encoder",
      "TARGET_ONE_HOT_ENCODER": "target_one_hot_encoder",
      "FEATURE_DROPPER": "feature_dropper",
      "VALUE_CLIPPER": "value_clipper",
      "TARGET_DROPPER": "target_dropper",
      "TARGET_FEATURE_ADDER": "target_feature_adder",
      "LABEL_ENCODER": "label_encoder",
      "XYSPLITTER": "xysplitter"
    }
  },
  "data_schema_keys": {
    "attributes": "attributes",
    "id_field": "idField",
    "target_attr_name": "targetField",
    "categorical": "CATEGORICAL",
    "numeric": "NUMERIC",
    "attr_type": "attributeType",
    "attr_name": "attributeName"
  },
  "valid_split": 0.1,
  "max_resample_of_minority_classes": 5
}
